odoo/addons/queue_job/README.rst
odoo/addons/queue_job/__init__.py
odoo/addons/queue_job/__manifest__.py
odoo/addons/queue_job/delay.py
odoo/addons/queue_job/exception.py
odoo/addons/queue_job/fields.py
odoo/addons/queue_job/job.py
odoo/addons/queue_job/post_init_hook.py
odoo/addons/queue_job/post_load.py
odoo/addons/queue_job/utils.py
odoo/addons/queue_job/controllers/__init__.py
odoo/addons/queue_job/controllers/main.py
odoo/addons/queue_job/data/queue_data.xml
odoo/addons/queue_job/data/queue_job_function_data.xml
odoo/addons/queue_job/i18n/de.po
odoo/addons/queue_job/i18n/es.po
odoo/addons/queue_job/i18n/it.po
odoo/addons/queue_job/i18n/nl.po
odoo/addons/queue_job/i18n/nl_NL.po
odoo/addons/queue_job/i18n/queue_job.pot
odoo/addons/queue_job/i18n/tr.po
odoo/addons/queue_job/i18n/tr_TR.po
odoo/addons/queue_job/i18n/zh_CN.po
odoo/addons/queue_job/jobrunner/__init__.py
odoo/addons/queue_job/jobrunner/__main__.py
odoo/addons/queue_job/jobrunner/channels.py
odoo/addons/queue_job/jobrunner/runner.py
odoo/addons/queue_job/migrations/18.0.1.0.0/pre-migrate.py
odoo/addons/queue_job/migrations/18.0.1.7.0/pre-migration.py
odoo/addons/queue_job/models/__init__.py
odoo/addons/queue_job/models/base.py
odoo/addons/queue_job/models/ir_model_fields.py
odoo/addons/queue_job/models/queue_job.py
odoo/addons/queue_job/models/queue_job_channel.py
odoo/addons/queue_job/models/queue_job_function.py
odoo/addons/queue_job/models/queue_job_lock.py
odoo/addons/queue_job/readme/CONFIGURE.md
odoo/addons/queue_job/readme/CONTRIBUTORS.md
odoo/addons/queue_job/readme/CREDITS.md
odoo/addons/queue_job/readme/DESCRIPTION.md
odoo/addons/queue_job/readme/HISTORY.md
odoo/addons/queue_job/readme/INSTALL.md
odoo/addons/queue_job/readme/ROADMAP.md
odoo/addons/queue_job/readme/USAGE.md
odoo/addons/queue_job/security/ir.model.access.csv
odoo/addons/queue_job/security/security.xml
odoo/addons/queue_job/static/description/icon.png
odoo/addons/queue_job/static/description/icon.svg
odoo_addon_queue_job-19.0.1.0.1.dist-info/METADATA
odoo_addon_queue_job-19.0.1.0.1.dist-info/WHEEL
odoo_addon_queue_job-19.0.1.0.1.dist-info/top_level.txt
odoo_addon_queue_job-19.0.1.0.1.dist-info/RECORD
